foiidea/__init__.py
foiidea/admin.py
foiidea/crawler.py
foiidea/models.py
foiidea/tasks.py
foiidea/tests.py
foiidea/urls.py
foiidea/views.py
foiidea/crawlers/__init__.py
foiidea/crawlers/rss.py
foiidea/management/__init__.py
foiidea/management/commands/__init__.py
foiidea/management/commands/load_feed.py
foiidea/management/commands/recalculate_idea_rank.py
foiidea/migrations/0001_initial.py
foiidea/migrations/0002_auto__add_field_article_score__add_field_article_rank__add_field_artic.py
foiidea/migrations/0003_auto__chg_field_article_url.py
foiidea/migrations/__init__.py
foiidea/templates/foiidea/_article.html
foiidea/templates/foiidea/base.html
foiidea/templates/foiidea/index.html
foiidea/templates/foiidea/show.html
froide_foiidea-0.0.1.dist-info/DESCRIPTION.rst
froide_foiidea-0.0.1.dist-info/METADATA
froide_foiidea-0.0.1.dist-info/pydist.json
froide_foiidea-0.0.1.dist-info/RECORD
froide_foiidea-0.0.1.dist-info/top_level.txt
froide_foiidea-0.0.1.dist-info/WHEEL
