Metadata-Version: 2.0
Name: froide-foiidea
Version: 0.0.1
Summary: Discovering FOI ideas in news articles
Home-page: https://github.com/stefanw/froide-foiidea
Author: Stefan Wehrmeyer
Author-email: mail@stefanwehrmeyer.com
License: BSD
Platform: UNKNOWN
Classifier: Development Status :: 4 - Beta
Classifier: Framework :: Django
Classifier: Intended Audience :: Developers
Classifier: License :: OSI Approved :: BSD License
Classifier: Operating System :: OS Independent
Classifier: Programming Language :: Python
Classifier: Programming Language :: Python :: 2.6
Classifier: Programming Language :: Python :: 2.7
Classifier: Programming Language :: Python :: 3.3
Classifier: Topic :: Utilities
Requires-Dist: Django
Requires-Dist: requests
Requires-Dist: celery
Requires-Dist: South
